apport/__init__.py
apport-1.0.dist-info/METADATA
apport-1.0.dist-info/WHEEL
apport-1.0.dist-info/top_level.txt
apport-1.0.dist-info/RECORD
